RenrenDuNengYongYingyu/README.md
RenrenDuNengYongYingyu/__init__.py
RenrenDuNengYongYingyu/__main__.py
RenrenDuNengYongYingyu/file.epub
RenrenDuNengYongYingyu/index.html
RenrenDuNengYongYingyu/css/__init__.py
RenrenDuNengYongYingyu/css/annotations.css
RenrenDuNengYongYingyu/css/main.css
RenrenDuNengYongYingyu/css/normalize.css
RenrenDuNengYongYingyu/css/popup.css
RenrenDuNengYongYingyu/font/__init__.py
RenrenDuNengYongYingyu/font/fontello.eot
RenrenDuNengYongYingyu/font/fontello.svg
RenrenDuNengYongYingyu/font/fontello.ttf
RenrenDuNengYongYingyu/font/fontello.woff
RenrenDuNengYongYingyu/img/__init__.py
RenrenDuNengYongYingyu/img/annotator-glyph-sprite.png
RenrenDuNengYongYingyu/img/annotator-icon-sprite.png
RenrenDuNengYongYingyu/img/apple-touch-icon.png
RenrenDuNengYongYingyu/img/cancelfullscreen.png
RenrenDuNengYongYingyu/img/close.png
RenrenDuNengYongYingyu/img/fullscreen.png
RenrenDuNengYongYingyu/img/loader.gif
RenrenDuNengYongYingyu/img/menu-icon.png
RenrenDuNengYongYingyu/img/save.png
RenrenDuNengYongYingyu/img/saved.png
RenrenDuNengYongYingyu/img/settings-s.png
RenrenDuNengYongYingyu/img/settings.png
RenrenDuNengYongYingyu/img/star.png
RenrenDuNengYongYingyu/js/__init__.py
RenrenDuNengYongYingyu/js/epub.js
RenrenDuNengYongYingyu/js/epub.min.js
RenrenDuNengYongYingyu/js/epub.min.map
RenrenDuNengYongYingyu/js/hooks.min.js
RenrenDuNengYongYingyu/js/hooks.min.map
RenrenDuNengYongYingyu/js/reader.js
RenrenDuNengYongYingyu/js/reader.js.map
RenrenDuNengYongYingyu/js/reader.min.js
RenrenDuNengYongYingyu/js/reader.min.map
RenrenDuNengYongYingyu/js/hooks/__init__.py
RenrenDuNengYongYingyu/js/hooks/extensions/__init__.py
RenrenDuNengYongYingyu/js/hooks/extensions/highlight.js
RenrenDuNengYongYingyu/js/libs/__init__.py
RenrenDuNengYongYingyu/js/libs/jquery.min.js
RenrenDuNengYongYingyu/js/libs/localforage.min.js
RenrenDuNengYongYingyu/js/libs/screenfull.js
RenrenDuNengYongYingyu/js/libs/screenfull.min.js
RenrenDuNengYongYingyu/js/libs/zip.min.js
renren_du_neng_yong_yingyu-2024.3.4.0.dist-info/METADATA
renren_du_neng_yong_yingyu-2024.3.4.0.dist-info/WHEEL
renren_du_neng_yong_yingyu-2024.3.4.0.dist-info/entry_points.txt
renren_du_neng_yong_yingyu-2024.3.4.0.dist-info/top_level.txt
renren_du_neng_yong_yingyu-2024.3.4.0.dist-info/RECORD
